cyclic_correlation/__init__.py
cyclic_correlation/cyclic_correlation.py
cyclic_correlation-0.1.12.dist-info/LICENSE.txt
cyclic_correlation-0.1.12.dist-info/METADATA
cyclic_correlation-0.1.12.dist-info/WHEEL
cyclic_correlation-0.1.12.dist-info/top_level.txt
cyclic_correlation-0.1.12.dist-info/RECORD
