Metadata-Version: 2.1
Name: cyclic_correlation
Version: 0.1.12
Summary: Cyclic cross-correlation utilities and Zadoff-Chu sequence generation
Home-page: https://github.com/noveroandrea/cyclic_correlation
Author: Andrea Novero
Author-email: your@email.com
License: BSD-3-Clause
Requires-Python: >=3.6
License-File: LICENSE.txt
Requires-Dist: numpy
